msgtopdf/__init__.py
msgtopdf/msgtopdf.py
msgtopdf/scripts/__init__.py
msgtopdf/scripts/msg2pdf.py
msgtopdf-0.1.6.dist-info/LICENSE
msgtopdf-0.1.6.dist-info/METADATA
msgtopdf-0.1.6.dist-info/WHEEL
msgtopdf-0.1.6.dist-info/entry_points.txt
msgtopdf-0.1.6.dist-info/top_level.txt
msgtopdf-0.1.6.dist-info/RECORD
