Metadata-Version: 2.1
Name: msgtopdf
Version: 0.1.6
Summary: Convert Outlook msg to PDF
Home-page: https://github.com/ushills/msgtopdf
Author: Ian Hill
Author-email: web@ushills.co.uk
License: UNKNOWN
Platform: UNKNOWN
Classifier: Programming Language :: Python :: 3
Classifier: Development Status :: 4 - Beta
Classifier: License :: OSI Approved :: MIT License
Classifier: Environment :: Win32 (MS Windows)
Classifier: Operating System :: Microsoft :: Windows
Requires-Python: >=3.6
Requires-Dist: pywin32
Requires-Dist: Click
Requires-Dist: Colorama
